scidata_lab/__init__.py
scidata_lab/exercises.py
scidata_lab-0.2.0.dist-info/METADATA
scidata_lab-0.2.0.dist-info/WHEEL
scidata_lab-0.2.0.dist-info/top_level.txt
scidata_lab-0.2.0.dist-info/RECORD
