Metadata-Version: 2.4
Name: scidata_lab
Version: 0.2.0
Summary: A demo package with machine learning exercises
Home-page: https://example.com
Author: Daniel
Author-email: your@email.com
License: MIT
Classifier: Programming Language :: Python :: 3
Classifier: License :: OSI Approved :: MIT License
Classifier: Operating System :: OS Independent
Requires-Python: >=3.7
Requires-Dist: pandas
Requires-Dist: numpy
Requires-Dist: matplotlib
Requires-Dist: scikit-learn
Requires-Dist: mlxtend
